{
  "id": "houseofstairs00slea",
  "title": "House of stairs",
  "creator": "Sleator, William",
  "date": "1974-01-01T00:00:00Z",
  "description": "Five fifteen-year-old orphans of widely varying personality characteristics are involuntarily placed in a house of endless stairs as subjects for a psychological experiment on conditioned human response",
  "mediatype": "texts",
  "collection": [
    "internetarchivebooks",
    "americana",
    "printdisabled",
    "inlibrary",
    "bostonuniversitylibraries-ol",
    "bpljordan-ol",
    "cnusd-ol",
    "unb-ol",
    "uni-ol",
    "universityofcoloradoboulder-ol"
  ],
  "subject": [
    "Science fiction",
    "Technology",
    "Brainwashing",
    "Psychology, Experimental"
  ],
  "downloads": 2016,
  "item_size": 185449371,
  "format": [
    "ACS Encrypted PDF",
    "Abbyy GZ",
    "Animated GIF",
    "Cloth Cover Detection Log",
    "DjVuTXT",
    "Djvu XML",
    "Dublin Core",
    "Item Tile",
    "JSON",
    "LCP Encrypted EPUB",
    "LCP Encrypted PDF",
    "MARC",
    "MARC Binary",
    "MARC Source",
    "Metadata",
    "Metadata Log",
    "OCLC xISBN JSON",
    "OCR Page Index",
    "OCR Search Text",
    "Page Numbers JSON",
    "Scandata",
    "Single Page Original JP2 Tar",
    "Single Page Processed JP2 ZIP",
    "Text PDF",
    "chOCR",
    "hOCR"
  ],
  "favorite_count": 26,
  "favorite_sample": [
    "acreofparadise",
    "benadrylblister5202",
    "blairbees9932",
    "blake_robison",
    "buttereliza"
  ]
}
