{
  "id": "TimeCod",
  "title": "Time Code",
  "creator": "Charles Eugene Anderson",
  "date": "2014-05-23T00:00:00Z",
  "description": "Time Code: The Best Collection of 52 Stories You Should Be Reading This Year The stories in ‘Time Code: The Best Collection of 52 Stories You Should Be Reading This Year’ are: 1- Big Bang Serenade 2- Mercury Heaven 3- Twilight's Last Gleaning 4- Ginkey's Garden 5- White Van 6- Finding Footprints 7- Timid Bunny 8- Red Moon 9- Some Pig 10- When the Doorbell Rings 11- Slush Pile 12- To Whom It May Concern 13- Blood Draw 14- Are We Superman? 15- Moon Tweets from the Sea of Tranquility, 1969 16- Time Code 17- The Ink Beneath 18- Christmas Poinsettias 19- After the Last Showing 20- September Remembered 21- Grafting In the Dark 22- Test of a Lifetime 23- Coffee Lover, Muffin Lover 24- Pink Unicorn Gunfight at the O.K. Corral 25- All I Want For Christmas...Beets 26- Sitting Next to the Bug 27- Sir John Falstaff Pleads With HAL: A Sonnet Not Penned By the Bard nor an Odyssey Presented By Kubrik 28- Mac Morris…Sick Day 29- Maidens and Monsters; Tokyo Footfalls 30- The Typist 31- There goes a Tenner...Beans 32- Excellent to Bad and Everything In-Between: A Quick Glance at Fredrick Culvert-Owen’s Credit Score 33-Eating Acrylic Pancakes with the Dictators at IHOP on my Birthday 34 -Fallen Hero 35- Girl Wrestler 36- Everything is Clear 37- Five Voice Mail Messages 38- Tourists of Apocalypse 39- Yellow Hair Lures Them All 40- Writer's Time 41- After the Game 42- Home Renovation TV 43- Bard's Muse 44- Fan Fic 45- Conan the Barber 46- Let's Make A Yggdrasil Tree Deal 47- Z-Garten 48- Stupid Fucking Story 49- Free Range Human 50- Sounds of Segregation 51- Nemo Found 52- Nona’s Christmas Cookies",
  "mediatype": "texts",
  "collection": [
    "opensource",
    "community"
  ],
  "subject": [
    "Science fiction",
    "fantasy",
    "flash fiction",
    "robots",
    "time travel",
    "micro friction"
  ],
  "downloads": 16100,
  "item_size": 38473439,
  "format": [
    "Abbyy GZ",
    "Archive BitTorrent",
    "DjVuTXT",
    "Djvu XML",
    "EPUB",
    "Item Tile",
    "JPEG",
    "JPEG Thumb",
    "MOBI",
    "Metadata",
    "OpenDocument Text Document",
    "Scandata",
    "Single Page Processed JP2 ZIP",
    "Text PDF"
  ],
  "favorite_count": 5,
  "favorite_sample": [
    "irohamca",
    "leaf01",
    "lemons666",
    "pere432",
    "refreshing_lemonade"
  ],
  "download_url": "https://archive.org/download/TimeCod/Time-Code-1519612152.epub",
  "download_url_cached": "scifi/content/TimeCod_epub.epub",
  "download_url_timestamp": "2025-03-13T08:43:36.262Z",
  "download_url_etag": "\"5a9372f1-ab903\"",
  "download_url_dl_duration": 0.535,
  "download_url_dl_mbps": 1.2526521058840172
}
