{
  "id": "warrencreepy-133",
  "title": "Creepy (Warren Publishing) Issue 133",
  "date": null,
  "description": "",
  "mediatype": "texts",
  "collection": [
    "creepy_warren",
    "pulpmagazinearchive",
    "additional_collections"
  ],
  "subject": [
    "creepy",
    "rush",
    "color",
    "warren",
    "order",
    "stories",
    "convaniant",
    "panallgan",
    "thrills",
    "rush order",
    "warren publishing",
    "screen thrills",
    "science fiction",
    "convaniant rush",
    "superb color",
    "noly panallgan",
    "loot super"
  ],
  "downloads": 2324,
  "item_size": 70886565,
  "format": [
    "Abbyy GZ",
    "Animated GIF",
    "Archive BitTorrent",
    "Comic Book RAR",
    "DjVu",
    "DjVuTXT",
    "Djvu XML",
    "Item Tile",
    "Metadata",
    "Scandata",
    "Single Page Processed JP2 ZIP",
    "Text PDF"
  ],
  "favorite_count": 2,
  "favorite_sample": [
    "glickmandigitalmedia",
    "torgo451"
  ],
  "download_url": "https://archive.org/download/warrencreepy-133/Creepy_133.pdf",
  "download_url_cached": "scifi/content/warrencreepy-133_text_pdf.pdf",
  "download_url_timestamp": "2025-03-13T16:39:27.914Z",
  "download_url_etag": "\"51dc332a-32d25b\"",
  "download_url_dl_duration": 1.185,
  "download_url_dl_mbps": 2.6804694646521456
}
