{
  "id": "galaxymagazine-1954-05",
  "title": "Galaxy Magazine (May 1954)",
  "date": "1954-05-01T00:00:00Z",
  "description": "",
  "mediatype": "texts",
  "collection": [
    "galaxymagazine",
    "magazine_rack",
    "additional_collections",
    "pulpmagazinearchive"
  ],
  "subject": [
    "roan",
    "galaxy",
    "fiction",
    "jim",
    "science",
    "murt",
    "hatcher",
    "saul",
    "transplat",
    "science fiction",
    "galaxy science",
    "open warfare",
    "bedside manner",
    "jim pearson",
    "galaxy publishing",
    "book club",
    "security officer",
    "phyllis sutton",
    "jim watched"
  ],
  "downloads": 4835,
  "item_size": 134273252,
  "format": [
    "Abbyy GZ",
    "Additional Text PDF",
    "Animated GIF",
    "Archive BitTorrent",
    "DjVu",
    "DjVuTXT",
    "Djvu XML",
    "EPUB",
    "Image Container PDF",
    "Item Tile",
    "Metadata",
    "Scandata",
    "Single Page Processed JP2 ZIP"
  ],
  "favorite_count": 1,
  "favorite_sample": [
    "eliz931"
  ],
  "download_url": "https://archive.org/download/galaxymagazine-1954-05/Galaxy_1954_05.epub",
  "download_url_cached": "scifi/content/galaxymagazine-1954-05_epub.epub",
  "download_url_timestamp": "2025-03-13T10:51:13.608Z",
  "download_url_etag": "\"6590cd63-4600ca\"",
  "download_url_dl_duration": 7.582,
  "download_url_dl_mbps": 0.5770499396217244
}
