{
  "id": "Galaxy_v01n02_1950-11",
  "title": "Galaxy v01n02 (1950 11)",
  "date": "1950-11-01T00:00:00Z",
  "description": "(Contents information excerpted from The Internet Speculative Fiction Database ) Art: Honeymoon in Hell by Don Sibley Misbegotten Missionary by John King Transfer Point by Paul Pierre Coming Attraction by Paul Callé To Serve Man by David Stone Time Quarry (Part 2 of 3) by David Stone Time Quarry (Part 2 of 3) [2] by David Stone Time Quarry (Part 2 of 3) [3] by David Stone Essays: It's All Yours by H. L. Gold Lands of Yesterday by L. Sprague de Camp Forecast (Galaxy, November 1950) by uncredited Next Month's Contents Page (Galaxy, November 1950) by uncredited Galaxy's Five Star Shelf (Galaxy, November 1950) by Groff Conklin Flying Saucer Contest by uncredited Novelettes: Honeymoon in Hell by Fredric Brown Transfer Point by Anthony Boucher Serial: Time Quarry (Part 2 of 3) by Clifford D. Simak Short Stories: Misbegotten Missionary by Isaac Asimov Coming Attraction by Fritz Leiber To Serve Man by Damon Knight",
  "mediatype": "texts",
  "collection": [
    "galaxymagazine",
    "magazine_rack",
    "additional_collections",
    "pulpmagazinearchive"
  ],
  "subject": [
    "sutton",
    "galaxy",
    "fiction",
    "science",
    "carmody",
    "vyrko",
    "man",
    "tion",
    "adams",
    "science fiction",
    "galaxy science",
    "time quarry",
    "sutton told",
    "president saunderson",
    "misbegotten missionary",
    "human race",
    "transfer point",
    "coming attraction",
    "flying saucer"
  ],
  "downloads": 2822,
  "item_size": 182960887,
  "format": [
    "Abbyy GZ",
    "Animated GIF",
    "Archive BitTorrent",
    "Comic Book RAR",
    "DjVu",
    "DjVuTXT",
    "Djvu XML",
    "EPUB",
    "Item Tile",
    "Metadata",
    "Scandata",
    "Single Page Processed JP2 ZIP",
    "Text PDF"
  ],
  "favorite_count": 15,
  "favorite_sample": [
    "alandia",
    "antong77",
    "arwingyoshi",
    "beltor",
    "buler"
  ],
  "download_url": "https://archive.org/download/Galaxy_v01n02_1950-11/Galaxy_v01n02_1950-11.epub",
  "download_url_cached": "scifi/content/Galaxy_v01n02_1950-11_epub.epub",
  "download_url_timestamp": "2025-03-13T14:45:50.141Z",
  "download_url_etag": "\"65acc89b-3be5f5c\"",
  "download_url_dl_duration": 8.848,
  "download_url_dl_mbps": 6.769697230720174
}
